Metadata-Version: 2.1
Name: payomail
Version: 9.0.0
Summary: mailing utilty
Home-page: https://github.com/Roshangedam/payomail
Author: Roshan Gedam
Author-email: roshangedam1998@gmail.com
Project-URL: Icon, https://github.com/Roshangedam/payomail/blob/master/payomail/images/icon.png
